{"opinion":{"isContribuable":false,"votes_total":8,"arguments_yes_count":0,"arguments_no_count":0,"id":451,"created_at":"2015-10-07T07:09:31+0200","updated_at":"2015-10-07T07:09:31+0200","body":"<h3>Article 1 &ndash; Smartphone pour tout intervenant &agrave; domicile<\/h3>\r\n\r\n<p>En tant que professionnel travaillant aupr&egrave;s des personnes &acirc;g&eacute;es handicap&eacute;es isol&eacute;es &agrave; domicile, tout &laquo;&nbsp;intervenant&nbsp;&raquo; doit disposer de smartphone<\/p>\r\n\r\n<ul>\r\n\t<li>pour &ecirc;tre identifi&eacute; d&rsquo;une mani&egrave;re certaine par un num&eacute;ro de mobile<\/li>\r\n\t<li>pour &ecirc;tre joignable d&rsquo;une mani&egrave;re certaine, et durable dans le temps<\/li>\r\n\t<li>pour &eacute;changer des messages de liaison, valant preuve, avec le &laquo;&nbsp;b&eacute;n&eacute;ficiaire&nbsp;&raquo;, sa famille, son tuteur, ensemble l&rsquo; &laquo;&nbsp;usager&nbsp;&raquo;<\/li>\r\n\t<li>pour se former d&#39;une mani&egrave;re continue &agrave; partir des cas pratiques enrichis quotidiennement par la communaut&eacute;<\/li>\r\n<\/ul>\r\n\r\n<h3>Article 2 &ndash; P&eacute;dagogie ouverte<\/h3>\r\n\r\n<p>Les formations relatives au maintien &agrave; domicile doivent &ecirc;tre ax&eacute;es sur des &eacute;tudes de cas pratiques, collaboratives, partag&eacute;es, ouvertes &agrave; tout intervenant, b&eacute;n&eacute;ficiaire, aidant, tuteur, ...<\/p>\r\n\r\n<p>Il faut mettre en place la formation en ligne ouverte &agrave; tous, an anglais MOOC, pour former et <strong>certifier <\/strong>tous les intervenants professionnels (&gt;300.000). Les aidants familiaux (&gt;4 millions) doivent pouvoir en profiter aussi.<\/p>\r\n\r\n<h3>Article 3 &ndash; Certification unique et lisible<\/h3>\r\n\r\n<p>Il faut une certification minimale unique pour tout intervenant s&rsquo;occupant de l&rsquo;aide quotidienne polyvalente des personnes &acirc;g&eacute;es handicap&eacute;es. La ma&icirc;trise des pratiques &eacute;l&eacute;mentaires de politesse et s&eacute;curit&eacute; doit &ecirc;tre certifi&eacute;e.<\/p>\r\n\r\n<p>Le mini-cv de l&rsquo;intervenant doit &ecirc;tre en ligne et communiqu&eacute; &agrave; l&rsquo;usager avant toute intervention.<\/p>\r\n\r\n<p>La certification doit y &ecirc;tre mentionn&eacute;e&nbsp;: date d&rsquo;obtention, num&eacute;ro de certification, l&rsquo;organisme certificateur, qui doit afficher ses cours en ligne, confirmer en ligne la validit&eacute; d&rsquo;un num&eacute;ro de certification.<\/p>\r\n\r\n<h3>Article 4 &ndash; Intervenant citoyen num&eacute;rique revaloris&eacute;<\/h3>\r\n\r\n<p>En tant que travailleur nomade aupr&egrave;s des personnes &acirc;g&eacute;es handicap&eacute;es isol&eacute;es, majoritairement exclues du num&eacute;rique, l&rsquo;intervenant doit &ecirc;tre int&eacute;gr&eacute; &agrave; la soci&eacute;t&eacute; num&eacute;rique pour aider les b&eacute;n&eacute;ficiaires &agrave; s&rsquo;int&eacute;grer &agrave; leur tour.<br \/>\r\n<br \/>\r\nLes comp&eacute;tences suivantes doivent devenir basiques dans le m&eacute;tier d&rsquo;intervenant :<\/p>\r\n\r\n<ul>\r\n\t<li>Le num&eacute;rique de base&nbsp;: smartphone, ordinateur, courriel, sms, agenda, navigation Internet<\/li>\r\n\t<li>Le num&eacute;rique professionnel&nbsp;: planifier, pointer, d&eacute;clarer, corriger, v&eacute;rifier les relev&eacute;s, &eacute;changer des messages de liaison valant preuve.<\/li>\r\n\t<li>Le num&eacute;rique social&nbsp;: r&eacute;seaux sociaux, plateformes de formation ouverte<\/li>\r\n<\/ul>","versions_count":0,"sources_count":0,"arguments_count":0,"author":{"username":"AiderNosParents","displayName":"AiderNosParents","uniqueId":"aidernosparents","isAdmin":false,"media":{"url":"\/media\/cache\/default_avatar\/default\/0001\/01\/811_default_avatar.jpg"},"vip":false,"_links":{"profile":"https:\/\/www.republique-numerique.fr\/profile\/aidernosparents","settings":"https:\/\/www.republique-numerique.fr\/profile\/edit-profile"}},"type":{"id":90,"title":"Section 1","subtitle":"Les Communs","voteWidgetType":2,"votesHelpText":"Pensez-vous que cette proposition permet d'atteindre les objectifs pr\u00e9sent\u00e9s dans l\u2019explication de l\u2019article ?","commentSystem":2,"color":"blue","versionable":true,"sourceable":true,"votesThreshold":null,"votesThresholdHelpText":null},"sources":[],"arguments":[],"modals":[],"votes":[{"user":{"username":"Christian Gayton","displayName":"Christian Gayton","uniqueId":"christiangayton","isAdmin":false,"media":null,"vip":false,"_links":{"profile":"https:\/\/www.republique-numerique.fr\/profile\/christiangayton","settings":"https:\/\/www.republique-numerique.fr\/profile\/edit-profile"}}},{"user":{"username":"Jeanne Varasco","displayName":"Jeanne Varasco","uniqueId":"jeannevarasco","isAdmin":false,"media":{"url":"\/media\/cache\/default_avatar\/default\/0001\/01\/139_default_avatar.jpg"},"vip":false,"_links":{"profile":"https:\/\/www.republique-numerique.fr\/profile\/jeannevarasco","settings":"https:\/\/www.republique-numerique.fr\/profile\/edit-profile"}}},{"user":{"username":"Christophe Osswald","displayName":"Christophe Osswald","uniqueId":"christopheosswald","isAdmin":false,"media":null,"vip":false,"_links":{"profile":"https:\/\/www.republique-numerique.fr\/profile\/christopheosswald","settings":"https:\/\/www.republique-numerique.fr\/profile\/edit-profile"}}},{"user":{"username":"Maltese Nadine","displayName":"Maltese Nadine","uniqueId":"maltesenadine","isAdmin":false,"media":{"url":"\/media\/cache\/default_avatar\/default\/0001\/01\/113_default_avatar.png"},"vip":false,"_links":{"profile":"https:\/\/www.republique-numerique.fr\/profile\/maltesenadine","settings":"https:\/\/www.republique-numerique.fr\/profile\/edit-profile"}}},{"user":{"username":"Pierre Lavayssi\u00e8re","displayName":"Pierre Lavayssi\u00e8re","uniqueId":"pierrelavayssiere","isAdmin":false,"media":null,"vip":false,"_links":{"profile":"https:\/\/www.republique-numerique.fr\/profile\/pierrelavayssiere","settings":"https:\/\/www.republique-numerique.fr\/profile\/edit-profile"}}}],"appendices":[{"body":"<p>Depuis 2010, l&rsquo;association <a class=\"ui-link\" href=\"http:\/\/www.aidernosparents.org\/\" style=\"color: rgb(51, 136, 204); font-weight: 700; font-family: sans-serif; font-size: 16px; font-style: normal; font-variant: normal; letter-spacing: normal; line-height: 18.9091px; orphans: auto; text-align: start; text-indent: 0px; text-transform: none; white-space: normal; widows: 1; word-spacing: 0px; -webkit-text-stroke-width: 0px; background-color: rgb(249, 249, 249);\">AiderNosParents<\/a> milite pour une formation en ligne pratique, collaborative, ouverte &agrave; tout intervenant &agrave; domicile, travailleur isol&eacute; marginalis&eacute;, et aux aidants familiaux qui s&#39;occupent de leurs proches &acirc;g&eacute;s handicap&eacute;s comme ils peuvent. Pr&eacute;cision : senior+aidant=usager.<\/p>\r\n\r\n<p>Les certifications existantes sont pl&eacute;thoriques, <strong>illisibles pour l&rsquo;usager<\/strong> : DEAVS, MCAD, ADVF, Titre professionnel employ&eacute; familial, Titre professionnel assistant de vie d&eacute;pendance, Bac Pro accompagnement, soins et services &agrave; la personne, BRS services et prestations du secteur sanitaire et social, &hellip;<\/p>\r\n\r\n<p>Les sujets de formation sont trop th&eacute;oriques : accompagnement fin de vie, troubles du comportement, Alzheimer, prise en charge de la d&eacute;pendance et du handicap, manutention, mobilit&eacute;, alimentation, bientraitance, maltraitance, &hellip;<\/p>\r\n\r\n<p>Les <strong>&eacute;tude de cas <\/strong>pratiques &eacute;l&eacute;mentaires de <strong>politesse et s&eacute;curit&eacute;<\/strong>&nbsp;<strong>r&eacute;clam&eacute;es par l&rsquo;usager<\/strong> sont ignor&eacute;es : comment j&rsquo;informe l&rsquo;usager la premi&egrave;re fois avant de venir et trace cet &eacute;v&egrave;nement dans le cahier de liaison, changement de planning, <strong>devoir d&#39;alerte<\/strong>, &hellip;<\/p>\r\n\r\n<p>En 2012-2013, dans le cadre d&rsquo;une politique de formation professionnelle <strong>ambitieuse<\/strong> compte tenu des enjeux de notre soci&eacute;t&eacute; en terme d&rsquo;accompagnement de personnes d&eacute;pendantes, l&rsquo;&eacute;tat a donn&eacute; 79 M&euro; &agrave; UNIFORMATION <a class=\"ui-link\" href=\"http:\/\/www.aidernosparents.org\/public\/uniformation-2012.png\" style=\"color: rgb(51, 136, 204); font-weight: 700;\">pi&egrave;ce<\/a>, et 22 M&euro; &agrave; AGEFOS PME.<\/p>\r\n\r\n<p>&laquo; UNIFORMATION aide &agrave; domicile &raquo; repr&eacute;sente 220.000 salari&eacute;s, 5.500 associations, dont ADMR et UNA.<\/p>\r\n\r\n<p>En 2012, l&rsquo;&eacute;tat a subventionn&eacute; 6 M&euro; &agrave; la CROIX ROUGE <a class=\"ui-link\" href=\"http:\/\/www.aidernosparents.org\/public\/croix-rouge-2012.png\" style=\"color: rgb(51, 136, 204); font-weight: 700;\">pi&egrave;ce<\/a>, pour moderniser.<\/p>\r\n\r\n<p>En 2013, l&rsquo;&eacute;tat a subventionn&eacute; 19 M&euro; &agrave; ADMR <a class=\"ui-link\" href=\"http:\/\/www.aidernosparents.org\/public\/admr-2013.png\" style=\"color: rgb(51, 136, 204); font-weight: 700;\">pi&egrave;ce<\/a>, pour la FOAD, Formation Ouverte A Distance, et pour moderniser son syst&egrave;me informatique.<\/p>\r\n\r\n<p>En 2014, l&rsquo;&eacute;tat a subventionn&eacute; 46 M&euro; &agrave; UNA <a class=\"ui-link\" href=\"http:\/\/www.aidernosparents.org\/\/public\/una-2014.png\" style=\"color: rgb(51, 136, 204); font-weight: 700;\">pi&egrave;ce<\/a>, pour moderniser.<\/p>\r\n\r\n<p>Mais ces 150 millions d&#39;euros d&#39;argent du contribuable pour former et moderniser le secteur associatif n&#39;a strictement rien apport&eacute; &agrave; l&#39;usager ! Quant aux intervenants, combien sur les 220.000 cibl&eacute;s ont obtenu le DEAVS niveau 5, objectif n&deg;1 selon UNIFORMATION ?<\/p>\r\n\r\n<p>Combien d&rsquo;intervenants disposent &agrave; ce jour de smartphone pour&nbsp;informer, s&rsquo;organiser,&nbsp;&eacute;changer des messages de liaison valant preuve (exigence n&deg;1 des usagers) ?<\/p>","type":{"title":"Explication de l'article"}}],"ranking":473,"is_trashed":false,"title":"E-learning pour 300.000 aides \u00e0 domicile et 4 millions d'aidants familiaux","votes_nok":1,"votes_ok":4,"votes_mitige":3,"_links":{"show":"https:\/\/www.republique-numerique.fr\/consultations\/projet-de-loi-numerique\/consultation\/consultation\/opinions\/section-1-les-communs\/e-learning-pour-300-000-aides-a-domicile-et-4-millions-d-aidants-familiaux","edit":"https:\/\/www.republique-numerique.fr\/consultations\/projet-de-loi-numerique\/consultation\/consultation\/opinions\/section-1-les-communs\/e-learning-pour-300-000-aides-a-domicile-et-4-millions-d-aidants-familiaux\/edit","report":"https:\/\/www.republique-numerique.fr\/consultations\/projet-de-loi-numerique\/consultation\/consultation\/opinions\/section-1-les-communs\/e-learning-pour-300-000-aides-a-domicile-et-4-millions-d-aidants-familiaux\/report","type":"https:\/\/www.republique-numerique.fr\/consultations\/projet-de-loi-numerique\/consultation\/consultation\/opinions\/section-1-les-communs"},"user_vote":null,"has_user_reported":false},"rankingThreshold":null,"opinionTerm":1}